MANIFEST.in
README.md
setup.py
bootstrap_themes/__init__.py
bootstrap_themes/themes.py
bootstrap_themes/static/bootstrap/fonts/glyphicons-halflings-regular.eot
bootstrap_themes/static/bootstrap/fonts/glyphicons-halflings-regular.svg
bootstrap_themes/static/bootstrap/fonts/glyphicons-halflings-regular.ttf
bootstrap_themes/static/bootstrap/fonts/glyphicons-halflings-regular.woff
bootstrap_themes/static/bootstrap/js/bootstrap.js
bootstrap_themes/static/bootstrap/js/bootstrap.min.js
bootstrap_themes/static/bootstrap/less/alerts.less
bootstrap_themes/static/bootstrap/less/badges.less
bootstrap_themes/static/bootstrap/less/bootstrap.less
bootstrap_themes/static/bootstrap/less/breadcrumbs.less
bootstrap_themes/static/bootstrap/less/button-groups.less
bootstrap_themes/static/bootstrap/less/buttons.less
bootstrap_themes/static/bootstrap/less/carousel.less
bootstrap_themes/static/bootstrap/less/close.less
bootstrap_themes/static/bootstrap/less/code.less
bootstrap_themes/static/bootstrap/less/component-animations.less
bootstrap_themes/static/bootstrap/less/dropdowns.less
bootstrap_themes/static/bootstrap/less/forms.less
bootstrap_themes/static/bootstrap/less/glyphicons.less
bootstrap_themes/static/bootstrap/less/grid.less
bootstrap_themes/static/bootstrap/less/input-groups.less
bootstrap_themes/static/bootstrap/less/jumbotron.less
bootstrap_themes/static/bootstrap/less/labels.less
bootstrap_themes/static/bootstrap/less/list-group.less
bootstrap_themes/static/bootstrap/less/media.less
bootstrap_themes/static/bootstrap/less/mixins.less
bootstrap_themes/static/bootstrap/less/modals.less
bootstrap_themes/static/bootstrap/less/navbar.less
bootstrap_themes/static/bootstrap/less/navs.less
bootstrap_themes/static/bootstrap/less/normalize.less
bootstrap_themes/static/bootstrap/less/pager.less
bootstrap_themes/static/bootstrap/less/pagination.less
bootstrap_themes/static/bootstrap/less/panels.less
bootstrap_themes/static/bootstrap/less/popovers.less
django_bootstrap_themes.egg-info/PKG-INFO
django_bootstrap_themes.egg-info/SOURCES.txt
django_bootstrap_themes.egg-info/dependency_links.txt
django_bootstrap_themes.egg-info/not-zip-safe
django_bootstrap_themes.egg-info/requires.txt
django_bootstrap_themes.egg-info/top_level.txt