Metadata-Version: 1.1
Name: django-bootstrap-themes
Version: 3.1.3
Summary: Bootstrap theme support for Django.
Home-page: http://github.com/no-dice/django-bootstrap-themes
Author: T. Scott Barnes
Author-email: tsbarnes@tsbarnes.com
License: MIT
Keywords: django bootstrap themes
Platform: UNKNOWN
Classifier: Development Status :: 5 - Production/Stable
Classifier: Environment :: Web Environment
Classifier: Intended Audience :: End Users/Desktop
Classifier: Natural Language :: English
Classifier: Operating System :: OS Independent
Classifier: Framework :: Django
Classifier: Programming Language :: Python
Classifier: Topic :: Internet :: WWW/HTTP :: Dynamic Content :: CGI Tools/Libraries
Classifier: Topic :: Utilities
Classifier: License :: OSI Approved :: MIT License
